graphene_scalars/__init__.py
graphene_scalars/currency.py
graphene_scalars/datetime.py
graphene_scalars/email_address.py
graphene_scalars/hex_color_code.py
graphene_scalars/hsl.py
graphene_scalars/ipv4.py
graphene_scalars/ipv6.py
graphene_scalars/json.py
graphene_scalars/negative_float.py
graphene_scalars/negative_int.py
graphene_scalars/non_empty_string.py
graphene_scalars/non_negative_float.py
graphene_scalars/non_negative_int.py
graphene_scalars/non_positive_float.py
graphene_scalars/non_positive_int.py
graphene_scalars/phone_number.py
graphene_scalars/port.py
graphene_scalars/positive_float.py
graphene_scalars/positive_int.py
graphene_scalars/rgb.py
graphene_scalars/url.py
graphene_scalars/uuid1.py
graphene_scalars-0.1.2.dist-info/WHEEL
graphene_scalars-0.1.2.dist-info/METADATA
graphene_scalars-0.1.2.dist-info/RECORD
